{
	"ID": "nexus.36",
	"Name": "3D Remake Soundtrack",
	"Author": "Fugsnarf",
	"AuthorLink": "",
	"ReleaseDate": "Nov 20, 2022",
	"Category": "Soundtrack",
	"Description": "Switch the entire soundtrack to that of the 3D Remake",
	"ReleaseNotes": "",
	"Link": "https://www.nexusmods.com/finalfantasy3pixelremaster/mods/36",
	"Version": "1.0",
	"InstallType": "Move",
	"Previews": [
		{
			"Url": "https://staticdelivery.nexusmods.com/mods/3942/images/36/36-1668968822-1617533534.png"
		}
	],
	"ModKind": {
		"Kinds": [
			"Nexus"
		],
		"NexusID": 36
	},
	"Compatibility": {
		"Require": [
			{
				"ModID": "unityplayer.enfyve"
			}
		]
	},
	"Downloadable": [
		{
			"Name": "3D Remake Soundtrack",
			"Version": "1.0",
			"Nexus": {
				"FileID": 104,
				"FileName": "3D Remake Soundtrack-36-1-0-1668968962.zip"
			}
		}
	],
	"Games": [
		{
			"Name": "FF3PR"
		}
	],
	"AlwaysDownload": [
		{
			"DownloadName": "3D Remake Soundtrack",
			"Dir": [
				{
					"From": "FINAL FANTASY III_Data",
					"To": "FINAL FANTASY III_Data",
					"Recursive": true
				}
			]
		}
	],
	"ConfigSelectionType": "Auto",
	"Hide": false,
	"VerifiedAsWorking": false,
	"IsManuallyCreated": true
}
